Metadata-Version: 2.1
Name: evm-py
Version: 0.10.1b1
Summary: Python implementation of the Ethereum Virtual Machine
Home-page: https://github.com/ethereum/py-evm
Author: Ethereum Foundation
Author-email: snakecharmers@ethereum.org
License: MIT
Keywords: ethereum blockchain evm
Classifier: Development Status :: 3 - Alpha
Classifier: Intended Audience :: Developers
Classifier: License :: OSI Approved :: MIT License
Classifier: Natural Language :: English
Classifier: Programming Language :: Python :: 3
Classifier: Programming Language :: Python :: 3.8
Classifier: Programming Language :: Python :: 3.9
Classifier: Programming Language :: Python :: 3.10
Classifier: Programming Language :: Python :: 3.11
Classifier: Programming Language :: Python :: 3.12
Requires-Python: >=3.8, <4
License-File: LICENSE
Requires-Dist: cached-property >=1.5.1
Requires-Dist: eth-bloom >=1.0.3
Requires-Dist: eth-keys >=0.4.0
Requires-Dist: eth-typing >=3.3.0
Requires-Dist: eth-utils >=2.0.0
Requires-Dist: lru-dict >=1.1.6
Requires-Dist: py-ecc >=1.4.7
Requires-Dist: rlp >=3.0.0
Requires-Dist: trie >=2.0.0
Requires-Dist: ckzg >=0.4.3
Provides-Extra: benchmark
Requires-Dist: termcolor >=1.1.0 ; extra == 'benchmark'
Requires-Dist: web3 >=6.0.0 ; extra == 'benchmark'
Provides-Extra: dev
Requires-Dist: build >=0.9.0 ; extra == 'dev'
Requires-Dist: bumpversion >=0.5.3 ; extra == 'dev'
Requires-Dist: ipython ; extra == 'dev'
Requires-Dist: pre-commit >=3.4.0 ; extra == 'dev'
Requires-Dist: tox >=4.0.0 ; extra == 'dev'
Requires-Dist: twine ; extra == 'dev'
Requires-Dist: wheel ; extra == 'dev'
Requires-Dist: py-evm >=0.8.0b1 ; extra == 'dev'
Requires-Dist: sphinx >=6.0.0 ; extra == 'dev'
Requires-Dist: sphinx-rtd-theme >=1.0.0 ; extra == 'dev'
Requires-Dist: sphinxcontrib-asyncio >=0.2.0 ; extra == 'dev'
Requires-Dist: towncrier <22,>=21 ; extra == 'dev'
Requires-Dist: cached-property >=1.5.1 ; extra == 'dev'
Requires-Dist: eth-bloom >=1.0.3 ; extra == 'dev'
Requires-Dist: eth-keys >=0.4.0 ; extra == 'dev'
Requires-Dist: eth-typing >=3.3.0 ; extra == 'dev'
Requires-Dist: eth-utils >=2.0.0 ; extra == 'dev'
Requires-Dist: lru-dict >=1.1.6 ; extra == 'dev'
Requires-Dist: py-ecc >=1.4.7 ; extra == 'dev'
Requires-Dist: rlp >=3.0.0 ; extra == 'dev'
Requires-Dist: trie >=2.0.0 ; extra == 'dev'
Requires-Dist: ckzg >=0.4.3 ; extra == 'dev'
Requires-Dist: factory-boy >=3.0.0 ; extra == 'dev'
Requires-Dist: hypothesis <7,>=6 ; extra == 'dev'
Requires-Dist: pytest >=7.0.0 ; extra == 'dev'
Requires-Dist: pytest-asyncio >=0.20.0 ; extra == 'dev'
Requires-Dist: pytest-cov >=4.0.0 ; extra == 'dev'
Requires-Dist: pytest-timeout >=2.0.0 ; extra == 'dev'
Requires-Dist: pytest-xdist >=3.0 ; extra == 'dev'
Provides-Extra: docs
Requires-Dist: py-evm >=0.8.0b1 ; extra == 'docs'
Requires-Dist: sphinx >=6.0.0 ; extra == 'docs'
Requires-Dist: sphinx-rtd-theme >=1.0.0 ; extra == 'docs'
Requires-Dist: sphinxcontrib-asyncio >=0.2.0 ; extra == 'docs'
Requires-Dist: towncrier <22,>=21 ; extra == 'docs'
Provides-Extra: eth
Requires-Dist: cached-property >=1.5.1 ; extra == 'eth'
Requires-Dist: eth-bloom >=1.0.3 ; extra == 'eth'
Requires-Dist: eth-keys >=0.4.0 ; extra == 'eth'
Requires-Dist: eth-typing >=3.3.0 ; extra == 'eth'
Requires-Dist: eth-utils >=2.0.0 ; extra == 'eth'
Requires-Dist: lru-dict >=1.1.6 ; extra == 'eth'
Requires-Dist: py-ecc >=1.4.7 ; extra == 'eth'
Requires-Dist: rlp >=3.0.0 ; extra == 'eth'
Requires-Dist: trie >=2.0.0 ; extra == 'eth'
Requires-Dist: ckzg >=0.4.3 ; extra == 'eth'
Provides-Extra: eth-extra
Requires-Dist: blake2b-py >=0.2.0 ; extra == 'eth-extra'
Requires-Dist: coincurve >=18.0.0 ; extra == 'eth-extra'
Provides-Extra: test
Requires-Dist: factory-boy >=3.0.0 ; extra == 'test'
Requires-Dist: hypothesis <7,>=6 ; extra == 'test'
Requires-Dist: pytest >=7.0.0 ; extra == 'test'
Requires-Dist: pytest-asyncio >=0.20.0 ; extra == 'test'
Requires-Dist: pytest-cov >=4.0.0 ; extra == 'test'
Requires-Dist: pytest-timeout >=2.0.0 ; extra == 'test'
Requires-Dist: pytest-xdist >=3.0 ; extra == 'test'
